swankernelenv/__init__.py
swankernelenv/_version.py
swankernelenv/cleaner.py
swankernelenv-1.0.0.dist-info/METADATA
swankernelenv-1.0.0.dist-info/WHEEL
swankernelenv-1.0.0.dist-info/top_level.txt
swankernelenv-1.0.0.dist-info/RECORD
